{
  "bookmakers": [
    {
      "key": "fanduel",
      "title": "FanDuel",
      "last_update": "2025-10-14T11:55:10Z",
      "markets": [
        {
          "key": "spreads",
          "last_update": "2025-10-14T11:55:10Z",
          "outcomes": [
            {
              "name": "Duke Blue Devils",
              "price": -110,
              "point": -1.5
            },
            {
              "name": "Georgia Tech Yellow Jackets",
              "price": -110,
              "point": 1.5
            }
          ]
        }
      ]
    },
    {
      "key": "draftkings",
      "title": "DraftKings",
      "last_update": "2025-10-14T11:54:38Z",
      "markets": [
        {
          "key": "spreads",
          "last_update": "2025-10-14T11:54:38Z",
          "outcomes": [
            {
              "name": "Duke Blue Devils",
              "price": -110,
              "point": -1.5
            },
            {
              "name": "Georgia Tech Yellow Jackets",
              "price": -110,
              "point": 1.5
            }
          ]
        }
      ]
    },
    {
      "key": "fanatics",
      "title": "Fanatics",
      "last_update": "2025-10-14T11:55:29Z",
      "markets": [
        {
          "key": "spreads",
          "last_update": "2025-10-14T11:55:29Z",
          "outcomes": [
            {
              "name": "Duke Blue Devils",
              "price": -110,
              "point": -1.5
            },
            {
              "name": "Georgia Tech Yellow Jackets",
              "price": -110,
              "point": 1.5
            }
          ]
        }
      ]
    },
    {
      "key": "betrivers",
      "title": "BetRivers",
      "last_update": "2025-10-14T11:53:57Z",
      "markets": [
        {
          "key": "spreads",
          "last_update": "2025-10-14T11:53:57Z",
          "outcomes": [
            {
              "name": "Duke Blue Devils",
              "price": -113,
              "point": -1.5
            },
            {
              "name": "Georgia Tech Yellow Jackets",
              "price": -110,
              "point": 1.5
            }
          ]
        }
      ]
    },
    {
      "key": "betmgm",
      "title": "BetMGM",
      "last_update": "2025-10-14T11:55:20Z",
      "markets": [
        {
          "key": "spreads",
          "last_update": "2025-10-14T11:55:19Z",
          "outcomes": [
            {
              "name": "Duke Blue Devils",
              "price": -110,
              "point": -1.5
            },
            {
              "name": "Georgia Tech Yellow Jackets",
              "price": -110,
              "point": 1.5
            }
          ]
        }
      ]
    },
    {
      "key": "williamhill_us",
      "title": "Caesars",
      "last_update": "2025-10-14T11:54:53Z",
      "markets": [
        {
          "key": "spreads",
          "last_update": "2025-10-14T11:54:53Z",
          "outcomes": [
            {
              "name": "Duke Blue Devils",
              "price": -110,
              "point": -1.5
            },
            {
              "name": "Georgia Tech Yellow Jackets",
              "price": -110,
              "point": 1.5
            }
          ]
        }
      ]
    },
    {
      "key": "lowvig",
      "title": "LowVig.ag",
      "last_update": "2025-10-14T11:55:09Z",
      "markets": [
        {
          "key": "spreads",
          "last_update": "2025-10-14T11:55:09Z",
          "outcomes": [
            {
              "name": "Duke Blue Devils",
              "price": -106,
              "point": -1.5
            },
            {
              "name": "Georgia Tech Yellow Jackets",
              "price": -106,
              "point": 1.5
            }
          ]
        }
      ]
    },
    {
      "key": "betonlineag",
      "title": "BetOnline.ag",
      "last_update": "2025-10-14T11:55:19Z",
      "markets": [
        {
          "key": "spreads",
          "last_update": "2025-10-14T11:55:19Z",
          "outcomes": [
            {
              "name": "Duke Blue Devils",
              "price": -110,
              "point": -1.5
            },
            {
              "name": "Georgia Tech Yellow Jackets",
              "price": -110,
              "point": 1.5
            }
          ]
        }
      ]
    },
    {
      "key": "bovada",
      "title": "Bovada",
      "last_update": "2025-10-14T11:55:35Z",
      "markets": [
        {
          "key": "spreads",
          "last_update": "2025-10-14T11:55:35Z",
          "outcomes": [
            {
              "name": "Duke Blue Devils",
              "price": -110,
              "point": -2.0
            },
            {
              "name": "Georgia Tech Yellow Jackets",
              "price": -110,
              "point": 2.0
            }
          ]
        }
      ]
    },
    {
      "key": "betus",
      "title": "BetUS",
      "last_update": "2025-10-14T11:55:20Z",
      "markets": [
        {
          "key": "spreads",
          "last_update": "2025-10-14T11:55:20Z",
          "outcomes": [
            {
              "name": "Duke Blue Devils",
              "price": -110,
              "point": -1.5
            },
            {
              "name": "Georgia Tech Yellow Jackets",
              "price": -110,
              "point": 1.5
            }
          ]
        }
      ]
    }
  ]
}