{"game_key": "20251101_0400_buffalo_bowling_green", "home_ytd": [{"season": 2025, "week": 1, "date": "2025-08-28", "opp": "Lafayette", "site": "H", "pf": 26.0, "pa": 7.0, "result": "W", "pr": 60.45, "pr_rank": 109, "sos": 41.84, "sos_rank": 117, "opp_pr": 50.04, "opp_pr_rank": 188, "opp_sos": 53.27, "opp_sos_rank": 209}, {"season": 2025, "week": 2, "date": "2025-09-06", "opp": "Cincinnati", "site": "A", "pf": 20.0, "pa": 34.0, "result": "L", "pr": 62.3, "pr_rank": 108, "sos": 61.12, "sos_rank": 79, "opp_pr": 72.05, "opp_pr_rank": 61, "opp_sos": 68.91, "opp_sos_rank": 33}, {"season": 2025, "week": 3, "date": "2025-09-13", "opp": "Liberty", "site": "H", "pf": 23.0, "pa": 13.0, "result": "W", "pr": 63.14, "pr_rank": 100, "sos": 59.75, "sos_rank": 128, "opp_pr": 62.08, "opp_pr_rank": 107, "opp_sos": 59.96, "opp_sos_rank": 125}, {"season": 2025, "week": 4, "date": "2025-09-20", "opp": "Louisville", "site": "A", "pf": 17.0, "pa": 40.0, "result": "L", "pr": 63.14, "pr_rank": 100, "sos": 59.75, "sos_rank": 128, "opp_pr": 81.06, "opp_pr_rank": 21, "opp_sos": 56.18, "opp_sos_rank": 172}, {"season": 2025, "week": 5, "date": "2025-09-27", "opp": "Ohio", "site": "A", "pf": 20.0, "pa": 35.0, "result": "L", "pr": 62.1, "pr_rank": 103, "sos": 69.34, "sos_rank": 34, "opp_pr": 69.26, "opp_pr_rank": 74, "opp_sos": 66.34, "opp_sos_rank": 54}, {"season": 2025, "week": 7, "date": "2025-10-11", "opp": "Toledo", "site": "H", "pf": 28.0, "pa": 23.0, "result": "W", "pr": 64.03, "pr_rank": 90, "sos": 67.98, "sos_rank": 48, "opp_pr": 70.19, "opp_pr_rank": 65, "opp_sos": 60.83, "opp_sos_rank": 115}, {"season": 2025, "week": 8, "date": "2025-10-18", "opp": "Central Michigan", "site": "H", "pf": 6.0, "pa": 27.0, "result": "L", "pr": 59.92, "pr_rank": 103, "sos": 65.61, "sos_rank": 70, "opp_pr": 59.63, "opp_pr_rank": 108, "opp_sos": 62.28, "opp_sos_rank": 106}, {"season": 2025, "week": 9, "date": "2025-10-25", "opp": "Kent State", "site": "A", "pf": NaN, "pa": NaN, "result": null, "pr": 59.92, "pr_rank": 103, "sos": 65.61, "sos_rank": 70, "opp_pr": 45.63, "opp_pr_rank": 132, "opp_sos": 68.36, "opp_sos_rank": 52}], "away_ytd": [{"season": 2025, "week": 1, "date": "2025-08-29", "opp": "Minnesota", "site": "A", "pf": 10.0, "pa": 23.0, "result": "L", "pr": 62.67, "pr_rank": 99, "sos": 81.19, "sos_rank": 19, "opp_pr": 77.46, "opp_pr_rank": 36, "opp_sos": 58.94, "opp_sos_rank": 67}, {"season": 2025, "week": 2, "date": "2025-09-06", "opp": "St. Francis (pa)", "site": "H", "pf": 45.0, "pa": 6.0, "result": "W", "pr": 65.79, "pr_rank": 87, "sos": 61.7, "sos_rank": 75, "opp_pr": null, "opp_pr_rank": null, "opp_sos": null, "opp_sos_rank": null}, {"season": 2025, "week": 3, "date": "2025-09-13", "opp": "Kent State", "site": "A", "pf": 31.0, "pa": 28.0, "result": "W", "pr": 62.52, "pr_rank": 104, "sos": 52.71, "sos_rank": 215, "opp_pr": 44.14, "opp_pr_rank": 237, "opp_sos": 59.52, "opp_sos_rank": 131}, {"season": 2025, "week": 4, "date": "2025-09-20", "opp": "Troy", "site": "H", "pf": 17.0, "pa": 21.0, "result": "L", "pr": 62.52, "pr_rank": 104, "sos": 52.71, "sos_rank": 215, "opp_pr": 64.02, "opp_pr_rank": 92, "opp_sos": 69.04, "opp_sos_rank": 40}, {"season": 2025, "week": 5, "date": "2025-09-27", "opp": "Uconn", "site": "H", "pf": 17.0, "pa": 20.0, "result": "L", "pr": 59.47, "pr_rank": 118, "sos": 55.73, "sos_rank": 169, "opp_pr": null, "opp_pr_rank": null, "opp_sos": null, "opp_sos_rank": null}, {"season": 2025, "week": 6, "date": "2025-10-04", "opp": "Eastern Michigan", "site": "H", "pf": 31.0, "pa": 30.0, "result": "W", "pr": 58.42, "pr_rank": 122, "sos": 54.72, "sos_rank": 174, "opp_pr": 53.11, "opp_pr_rank": 155, "opp_sos": 62.07, "opp_sos_rank": 99}, {"season": 2025, "week": 8, "date": "2025-10-18", "opp": "Massachusetts", "site": "A", "pf": 28.0, "pa": 21.0, "result": "W", "pr": 57.96, "pr_rank": 113, "sos": 54.45, "sos_rank": 152, "opp_pr": 42.09, "opp_pr_rank": 134, "opp_sos": 60.34, "opp_sos_rank": 118}, {"season": 2025, "week": 9, "date": "2025-10-25", "opp": "Akron", "site": "H", "pf": NaN, "pa": NaN, "result": null, "pr": 57.96, "pr_rank": 113, "sos": 54.45, "sos_rank": 152, "opp_pr": 50.21, "opp_pr_rank": 128, "opp_sos": 60.51, "opp_sos_rank": 117}], "home_prev": [{"season": 2024, "week": 1, "date": "2024-08-29", "opp": "Fordham", "site": "H", "pf": 41, "pa": 17, "result": "W", "pr": 61.7, "pr_rank": 107, "sos": 40.0, "sos_rank": 196, "opp_pr": 43.82, "opp_pr_rank": 191, "opp_sos": 65.52, "opp_sos_rank": 93}, {"season": 2024, "week": 2, "date": "2024-09-07", "opp": "Penn State", "site": "A", "pf": 27, "pa": 34, "result": "L", "pr": 64.25, "pr_rank": 93, "sos": 63.12, "sos_rank": 91, "opp_pr": 85.6, "opp_pr_rank": 10, "opp_sos": 70.77, "opp_sos_rank": 34}, {"season": 2024, "week": 4, "date": "2024-09-21", "opp": "Texas Aandm", "site": "A", "pf": 20, "pa": 26, "result": "L", "pr": 66.34, "pr_rank": 85, "sos": 77.02, "sos_rank": 3, "opp_pr": 81.93, "opp_pr_rank": 22, "opp_sos": 69.5, "opp_sos_rank": 30}, {"season": 2024, "week": 5, "date": "2024-09-28", "opp": "Old Dominion", "site": "H", "pf": 27, "pa": 30, "result": "L", "pr": 64.55, "pr_rank": 97, "sos": 69.64, "sos_rank": 37, "opp_pr": 63.1, "opp_pr_rank": 105, "opp_sos": 71.23, "opp_sos_rank": 25}, {"season": 2024, "week": 6, "date": "2024-10-05", "opp": "Akron", "site": "A", "pf": 27, "pa": 20, "result": "W", "pr": 62.65, "pr_rank": 98, "sos": 62.94, "sos_rank": 100, "opp_pr": 48.82, "opp_pr_rank": 174, "opp_sos": 69.93, "opp_sos_rank": 39}, {"season": 2024, "week": 7, "date": "2024-10-12", "opp": "Northern Illinois", "site": "H", "pf": 7, "pa": 17, "result": "L", "pr": 62.65, "pr_rank": 98, "sos": 62.94, "sos_rank": 100, "opp_pr": 62.23, "opp_pr_rank": 100, "opp_sos": 55.94, "opp_sos_rank": 148}, {"season": 2024, "week": 8, "date": "2024-10-19", "opp": "Kent State", "site": "H", "pf": 27, "pa": 6, "result": "W", "pr": 62.65, "pr_rank": 98, "sos": 62.94, "sos_rank": 100, "opp_pr": 41.57, "opp_pr_rank": 214, "opp_sos": 73.8, "opp_sos_rank": 13}, {"season": 2024, "week": 9, "date": "2024-10-26", "opp": "Toledo", "site": "A", "pf": 41, "pa": 26, "result": "W", "pr": 62.65, "pr_rank": 98, "sos": 62.94, "sos_rank": 100, "opp_pr": 71.38, "opp_pr_rank": 7, "opp_sos": 49.48, "opp_sos_rank": 132}, {"season": 2024, "week": 11, "date": "2024-11-06", "opp": "Central Michigan", "site": "A", "pf": 23, "pa": 13, "result": "W", "pr": 64.02, "pr_rank": 97, "sos": 60.18, "sos_rank": 120, "opp_pr": 53.08, "opp_pr_rank": 144, "opp_sos": 59.18, "opp_sos_rank": 125}, {"season": 2024, "week": 12, "date": "2024-11-13", "opp": "Western Michigan", "site": "H", "pf": 31, "pa": 13, "result": "W", "pr": 65.33, "pr_rank": 91, "sos": 59.33, "sos_rank": 122, "opp_pr": 57.58, "opp_pr_rank": 121, "opp_sos": 60.43, "opp_sos_rank": 116}, {"season": 2024, "week": 13, "date": "2024-11-23", "opp": "Ball State", "site": "A", "pf": 38, "pa": 13, "result": "W", "pr": 66.63, "pr_rank": 85, "sos": 58.41, "sos_rank": 127, "opp_pr": 52.73, "opp_pr_rank": 146, "opp_sos": 62.12, "opp_sos_rank": 102}, {"season": 2024, "week": 14, "date": "2024-11-29", "opp": "Miami (oh)", "site": "H", "pf": 12, "pa": 28, "result": "L", "pr": 64.54, "pr_rank": 93, "sos": 59.33, "sos_rank": 122, "opp_pr": null, "opp_pr_rank": null, "opp_sos": null, "opp_sos_rank": null}], "away_prev": [{"season": 2024, "week": 1, "date": "2024-08-29", "opp": "Lafayette", "site": "H", "pf": 30, "pa": 13, "result": "W", "pr": 53.53, "pr_rank": 142, "sos": 44.66, "sos_rank": 174, "opp_pr": 48.48, "opp_pr_rank": 167, "opp_sos": 57.35, "opp_sos_rank": 119}, {"season": 2024, "week": 2, "date": "2024-09-07", "opp": "Missouri", "site": "A", "pf": 0, "pa": 38, "result": "L", "pr": 53.99, "pr_rank": 145, "sos": 67.36, "sos_rank": 58, "opp_pr": 85.52, "opp_pr_rank": 11, "opp_sos": 45.69, "opp_sos_rank": 219}, {"season": 2024, "week": 3, "date": "2024-09-14", "opp": "Massachusetts", "site": "H", "pf": 34, "pa": 3, "result": "W", "pr": 56.73, "pr_rank": 129, "sos": 55.45, "sos_rank": 157, "opp_pr": 44.2, "opp_pr_rank": 197, "opp_sos": 61.21, "opp_sos_rank": 107}, {"season": 2024, "week": 4, "date": "2024-09-21", "opp": "Northern Illinois", "site": "A", "pf": 23, "pa": 20, "result": "W", "pr": 58.46, "pr_rank": 124, "sos": 58.86, "sos_rank": 138, "opp_pr": 64.12, "opp_pr_rank": 99, "opp_sos": 56.89, "opp_sos_rank": 151}, {"season": 2024, "week": 5, "date": "2024-09-28", "opp": "Uconn", "site": "A", "pf": 3, "pa": 47, "result": "L", "pr": 54.55, "pr_rank": 141, "sos": 61.62, "sos_rank": 106, "opp_pr": null, "opp_pr_rank": null, "opp_sos": null, "opp_sos_rank": null}, {"season": 2024, "week": 7, "date": "2024-10-12", "opp": "Toledo", "site": "H", "pf": 30, "pa": 15, "result": "W", "pr": 54.95, "pr_rank": 139, "sos": 60.55, "sos_rank": 114, "opp_pr": 69.29, "opp_pr_rank": 75, "opp_sos": 57.76, "opp_sos_rank": 130}, {"season": 2024, "week": 8, "date": "2024-10-19", "opp": "Western Michigan", "site": "H", "pf": 41, "pa": 48, "result": "L", "pr": 54.95, "pr_rank": 139, "sos": 60.55, "sos_rank": 114, "opp_pr": 57.75, "opp_pr_rank": 125, "opp_sos": 67.08, "opp_sos_rank": 67}, {"season": 2024, "week": 9, "date": "2024-10-26", "opp": "Ohio", "site": "A", "pf": 16, "pa": 47, "result": "L", "pr": 54.95, "pr_rank": 139, "sos": 60.55, "sos_rank": 114, "opp_pr": 70.11, "opp_pr_rank": 16, "opp_sos": 76.05, "opp_sos_rank": 51}, {"season": 2024, "week": 10, "date": "2024-11-02", "opp": "Akron", "site": "A", "pf": 41, "pa": 30, "result": "W", "pr": 55.17, "pr_rank": 137, "sos": 59.33, "sos_rank": 125, "opp_pr": 49.34, "opp_pr_rank": 169, "opp_sos": 64.28, "opp_sos_rank": 87}, {"season": 2024, "week": 12, "date": "2024-11-13", "opp": "Ball State", "site": "H", "pf": 51, "pa": 48, "result": "W", "pr": 55.59, "pr_rank": 131, "sos": 58.85, "sos_rank": 126, "opp_pr": 54.48, "opp_pr_rank": 138, "opp_sos": 62.14, "opp_sos_rank": 103}, {"season": 2024, "week": 13, "date": "2024-11-21", "opp": "Eastern Michigan", "site": "A", "pf": 37, "pa": 20, "result": "W", "pr": 57.51, "pr_rank": 123, "sos": 58.26, "sos_rank": 129, "opp_pr": 52.45, "opp_pr_rank": 149, "opp_sos": 56.55, "opp_sos_rank": 136}, {"season": 2024, "week": 14, "date": "2024-11-27", "opp": "Kent State", "site": "H", "pf": 43, "pa": 7, "result": "W", "pr": 59.06, "pr_rank": 118, "sos": 56.46, "sos_rank": 136, "opp_pr": 37.24, "opp_pr_rank": 231, "opp_sos": 63.47, "opp_sos_rank": 94}]}