{"game_key": "20251004_1930_texas_longhorns_florida", "home_ytd": [{"season": 2025, "week": 1, "date": "2025-08-30", "opp": "Long Island University", "site": "H", "pf": 55, "pa": 0, "result": "W", "ats": null, "to_margin": null, "pr": 87.91, "pr_rank": 12, "sos": 37.87, "sos_rank": 128, "opp_pr": null, "opp_pr_rank": null, "opp_sos": null, "opp_sos_rank": null}, {"season": 2025, "week": 2, "date": "2025-09-06", "opp": "South Florida", "site": "H", "pf": 16, "pa": 18, "result": "L", "ats": null, "to_margin": null, "pr": 81.05, "pr_rank": 24, "sos": 80.4, "sos_rank": 1, "opp_pr": 77.87, "opp_pr_rank": 34, "opp_sos": 67.05, "opp_sos_rank": 64}, {"season": 2025, "week": 3, "date": "2025-09-13", "opp": "Lsu", "site": "A", "pf": 10, "pa": 20, "result": "L", "ats": null, "to_margin": null, "pr": 81.05, "pr_rank": 24, "sos": 80.4, "sos_rank": 1, "opp_pr": 86.31, "opp_pr_rank": 10, "opp_sos": 76.24, "opp_sos_rank": 7}, {"season": 2025, "week": 4, "date": "2025-09-20", "opp": "Miami", "site": "A", "pf": 7, "pa": 26, "result": "L", "ats": null, "to_margin": null, "pr": 81.05, "pr_rank": 24, "sos": 80.4, "sos_rank": 1, "opp_pr": null, "opp_pr_rank": null, "opp_sos": null, "opp_sos_rank": null}], "away_ytd": [{"season": 2025, "week": 1, "date": "2025-08-30", "opp": "Ohio State Buckeyes", "site": "A", "pf": 7, "pa": 14, "result": "L", "ats": null, "to_margin": null, "pr": 93.58, "pr_rank": 5, "sos": 101.04, "sos_rank": 1, "opp_pr": 97.31, "opp_pr_rank": 1, "opp_sos": 89.86, "opp_sos_rank": 9}, {"season": 2025, "week": 2, "date": "2025-09-06", "opp": "San José State", "site": "H", "pf": 38, "pa": 7, "result": "W", "ats": null, "to_margin": null, "pr": 87.49, "pr_rank": 9, "sos": 71.93, "sos_rank": 28, "opp_pr": null, "opp_pr_rank": null, "opp_sos": null, "opp_sos_rank": null}, {"season": 2025, "week": 3, "date": "2025-09-13", "opp": "Utep", "site": "H", "pf": 27, "pa": 10, "result": "W", "ats": null, "to_margin": null, "pr": 87.49, "pr_rank": 9, "sos": 71.93, "sos_rank": 28, "opp_pr": 54.7, "opp_pr_rank": 118, "opp_sos": 57.37, "opp_sos_rank": 137}, {"season": 2025, "week": 4, "date": "2025-09-21", "opp": "Sam Houston", "site": "H", "pf": 55, "pa": 0, "result": "W", "ats": null, "to_margin": null, "pr": 87.49, "pr_rank": 9, "sos": 71.93, "sos_rank": 28, "opp_pr": null, "opp_pr_rank": null, "opp_sos": null, "opp_sos_rank": null}], "home_prev": [{"season": 2024, "week": 1, "date": "2024-08-31", "opp": "Miami", "site": "H", "pf": 17, "pa": 41, "result": "L", "ats": null, "to_margin": null, "pr": 75.86, "pr_rank": 39, "sos": 80.86, "sos_rank": 30, "opp_pr": null, "opp_pr_rank": null, "opp_sos": null, "opp_sos_rank": null}, {"season": 2024, "week": 2, "date": "2024-09-07", "opp": "Samford", "site": "H", "pf": 45, "pa": 7, "result": "W", "ats": null, "to_margin": null, "pr": 76.31, "pr_rank": 38, "sos": 62.02, "sos_rank": 103, "opp_pr": 44.16, "opp_pr_rank": 191, "opp_sos": 56.96, "opp_sos_rank": 147}, {"season": 2024, "week": 3, "date": "2024-09-14", "opp": "Texas Aandm", "site": "H", "pf": 20, "pa": 33, "result": "L", "ats": null, "to_margin": null, "pr": 75.69, "pr_rank": 42, "sos": 73.12, "sos_rank": 19, "opp_pr": 83.51, "opp_pr_rank": 18, "opp_sos": 72.81, "opp_sos_rank": 20}, {"season": 2024, "week": 4, "date": "2024-09-21", "opp": "Mississippi State", "site": "A", "pf": 45, "pa": 28, "result": "W", "ats": null, "to_margin": null, "pr": 76.68, "pr_rank": 36, "sos": 71.57, "sos_rank": 21, "opp_pr": 67.46, "opp_pr_rank": 80, "opp_sos": 66.41, "opp_sos_rank": 61}, {"season": 2024, "week": 6, "date": "2024-10-05", "opp": "Ucf", "site": "H", "pf": 24, "pa": 13, "result": "W", "ats": null, "to_margin": null, "pr": 77.43, "pr_rank": 37, "sos": 72.34, "sos_rank": 26, "opp_pr": null, "opp_pr_rank": null, "opp_sos": null, "opp_sos_rank": null}, {"season": 2024, "week": 7, "date": "2024-10-12", "opp": "Tennessee", "site": "A", "pf": 17, "pa": 23, "result": "L", "ats": null, "to_margin": null, "pr": 77.43, "pr_rank": 37, "sos": 72.34, "sos_rank": 26, "opp_pr": 87.84, "opp_pr_rank": 8, "opp_sos": 60.11, "opp_sos_rank": 66}, {"season": 2024, "week": 8, "date": "2024-10-19", "opp": "Kentucky", "site": "H", "pf": 48, "pa": 20, "result": "W", "ats": null, "to_margin": null, "pr": 77.43, "pr_rank": 37, "sos": 72.34, "sos_rank": 26, "opp_pr": 82.15, "opp_pr_rank": 19, "opp_sos": 74.19, "opp_sos_rank": 5}, {"season": 2024, "week": 10, "date": "2024-11-02", "opp": "Georgia Bulldogs", "site": "A", "pf": 20, "pa": 34, "result": "L", "ats": null, "to_margin": null, "pr": 80.15, "pr_rank": 24, "sos": 77.36, "sos_rank": 6, "opp_pr": 92.81, "opp_pr_rank": 1, "opp_sos": 77.52, "opp_sos_rank": 5}, {"season": 2024, "week": 11, "date": "2024-11-09", "opp": "Texas Longhorns", "site": "A", "pf": 17, "pa": 49, "result": "L", "ats": null, "to_margin": null, "pr": 78.12, "pr_rank": 29, "sos": 78.83, "sos_rank": 3, "opp_pr": 92.46, "opp_pr_rank": 2, "opp_sos": 71.37, "opp_sos_rank": 47}, {"season": 2024, "week": 12, "date": "2024-11-16", "opp": "Lsu", "site": "H", "pf": 27, "pa": 16, "result": "W", "ats": null, "to_margin": null, "pr": 79.91, "pr_rank": 26, "sos": 78.92, "sos_rank": 4, "opp_pr": 81.94, "opp_pr_rank": 18, "opp_sos": 79.2, "opp_sos_rank": 3}, {"season": 2024, "week": 13, "date": "2024-11-23", "opp": "Ole Miss", "site": "H", "pf": 24, "pa": 17, "result": "W", "ats": null, "to_margin": null, "pr": 81.69, "pr_rank": 20, "sos": 79.52, "sos_rank": 1, "opp_pr": null, "opp_pr_rank": null, "opp_sos": null, "opp_sos_rank": null}, {"season": 2024, "week": 14, "date": "2024-12-01", "opp": "Florida State", "site": "A", "pf": 31, "pa": 11, "result": "W", "ats": null, "to_margin": null, "pr": 81.99, "pr_rank": 19, "sos": 78.08, "sos_rank": 4, "opp_pr": 66.86, "opp_pr_rank": 81, "opp_sos": 76.23, "opp_sos_rank": 19}], "away_prev": [{"season": 2024, "week": 1, "date": "2024-08-31", "opp": "Colorado State", "site": "H", "pf": 52, "pa": 0, "result": "W", "ats": null, "to_margin": null, "pr": 95.78, "pr_rank": 2, "sos": 58.94, "sos_rank": 113, "opp_pr": 62.76, "opp_pr_rank": 101, "opp_sos": 99.61, "opp_sos_rank": 1}, {"season": 2024, "week": 2, "date": "2024-09-07", "opp": "Michigan", "site": "A", "pf": 31, "pa": 12, "result": "W", "ats": null, "to_margin": null, "pr": 95.56, "pr_rank": 2, "sos": 72.79, "sos_rank": 20, "opp_pr": 84.12, "opp_pr_rank": 13, "opp_sos": 79.92, "opp_sos_rank": 5}, {"season": 2024, "week": 3, "date": "2024-09-14", "opp": "Utsa", "site": "H", "pf": 56, "pa": 7, "result": "W", "ats": null, "to_margin": null, "pr": 95.09, "pr_rank": 1, "sos": 67.69, "sos_rank": 50, "opp_pr": 64.94, "opp_pr_rank": 93, "opp_sos": 72.07, "opp_sos_rank": 25}, {"season": 2024, "week": 4, "date": "2024-09-22", "opp": "Ul Monroe", "site": "H", "pf": 51, "pa": 3, "result": "W", "ats": null, "to_margin": null, "pr": 95.02, "pr_rank": 1, "sos": 63.06, "sos_rank": 93, "opp_pr": null, "opp_pr_rank": null, "opp_sos": null, "opp_sos_rank": null}, {"season": 2024, "week": 5, "date": "2024-09-28", "opp": "Mississippi State", "site": "H", "pf": 35, "pa": 13, "result": "W", "ats": null, "to_margin": null, "pr": 93.72, "pr_rank": 1, "sos": 63.97, "sos_rank": 86, "opp_pr": 68.98, "opp_pr_rank": 71, "opp_sos": 72, "opp_sos_rank": 20}, {"season": 2024, "week": 7, "date": "2024-10-12", "opp": "Oklahoma", "site": "A", "pf": 34, "pa": 3, "result": "W", "ats": null, "to_margin": null, "pr": 90.53, "pr_rank": 3, "sos": 61.67, "sos_rank": 57, "opp_pr": 86.99, "opp_pr_rank": 9, "opp_sos": 66.36, "opp_sos_rank": 23}, {"season": 2024, "week": 8, "date": "2024-10-19", "opp": "Georgia Bulldogs", "site": "H", "pf": 15, "pa": 30, "result": "L", "ats": null, "to_margin": null, "pr": 90.53, "pr_rank": 3, "sos": 61.67, "sos_rank": 57, "opp_pr": 90.05, "opp_pr_rank": 4, "opp_sos": 57.67, "opp_sos_rank": 73}, {"season": 2024, "week": 9, "date": "2024-10-26", "opp": "Vanderbilt", "site": "A", "pf": 27, "pa": 24, "result": "W", "ats": null, "to_margin": null, "pr": 90.53, "pr_rank": 3, "sos": 61.67, "sos_rank": 57, "opp_pr": 71.08, "opp_pr_rank": 68, "opp_sos": 70.95, "opp_sos_rank": 31}, {"season": 2024, "week": 11, "date": "2024-11-09", "opp": "Florida", "site": "H", "pf": 49, "pa": 17, "result": "W", "ats": null, "to_margin": null, "pr": 92.46, "pr_rank": 2, "sos": 71.37, "sos_rank": 47, "opp_pr": 78.12, "opp_pr_rank": 29, "opp_sos": 78.83, "opp_sos_rank": 3}, {"season": 2024, "week": 12, "date": "2024-11-16", "opp": "Arkansas", "site": "A", "pf": 20, "pa": 10, "result": "W", "ats": null, "to_margin": null, "pr": 92.33, "pr_rank": 2, "sos": 73.05, "sos_rank": 38, "opp_pr": 76.6, "opp_pr_rank": 39, "opp_sos": 76.42, "opp_sos_rank": 12}, {"season": 2024, "week": 13, "date": "2024-11-23", "opp": "Kentucky", "site": "H", "pf": 31, "pa": 14, "result": "W", "ats": null, "to_margin": null, "pr": 92.02, "pr_rank": 3, "sos": 73.36, "sos_rank": 39, "opp_pr": 74.92, "opp_pr_rank": 50, "opp_sos": 77.56, "opp_sos_rank": 6}, {"season": 2024, "week": 14, "date": "2024-12-01", "opp": "Texas Aandm", "site": "A", "pf": 17, "pa": 7, "result": "W", "ats": null, "to_margin": null, "pr": 91.98, "pr_rank": 2, "sos": 74.35, "sos_rank": 32, "opp_pr": 82.27, "opp_pr_rank": 18, "opp_sos": 76.25, "opp_sos_rank": 18}, {"season": 2024, "week": 15, "date": "2024-12-07", "opp": "Georgia Bulldogs", "site": "H", "pf": 19, "pa": 22, "result": "L", "ats": null, "to_margin": null, "pr": 91.2, "pr_rank": 4, "sos": 75.75, "sos_rank": 20, "opp_pr": 90.11, "opp_pr_rank": 5, "opp_sos": 78.66, "opp_sos_rank": 4}]}