{"game_key": "20251102_1800_det_min", "home_ytd": [{"season": 2025, "week": 1, "date": "2025-09-07", "opp": "Green Bay Packers", "site": "A", "pf": 13, "pa": 27, "result": "L", "pr": 29.97, "pr_rank": NaN, "sos": 20.73, "sos_rank": 7.0, "opp_pr": 26.41, "opp_pr_rank": NaN, "opp_sos": 20.61, "opp_sos_rank": 10.0}, {"season": 2025, "week": 2, "date": "2025-09-14", "opp": "Chicago Bears", "site": "H", "pf": 52, "pa": 21, "result": "W", "pr": 24.65, "pr_rank": NaN, "sos": 21.82, "sos_rank": 7.0, "opp_pr": 18.47, "opp_pr_rank": NaN, "opp_sos": 22.49, "opp_sos_rank": 4.0}, {"season": 2025, "week": 3, "date": "2025-09-23", "opp": "Baltimore Ravens", "site": "A", "pf": 38, "pa": 30, "result": "W", "pr": NaN, "pr_rank": NaN, "sos": NaN, "sos_rank": NaN, "opp_pr": NaN, "opp_pr_rank": NaN, "opp_sos": NaN, "opp_sos_rank": NaN}, {"season": 2025, "week": 4, "date": "2025-09-28", "opp": "Cleveland Browns", "site": "H", "pf": 34, "pa": 10, "result": "W", "pr": 25.64, "pr_rank": NaN, "sos": 21.28, "sos_rank": 9.0, "opp_pr": 15.24, "opp_pr_rank": NaN, "opp_sos": 24.0, "opp_sos_rank": 1.0}, {"season": 2025, "week": 5, "date": "2025-10-05", "opp": "Cincinnati Bengals", "site": "A", "pf": 37, "pa": 24, "result": "W", "pr": 25.64, "pr_rank": NaN, "sos": 15.4, "sos_rank": 31.0, "opp_pr": 20.36, "opp_pr_rank": NaN, "opp_sos": 21.28, "opp_sos_rank": 9.0}, {"season": 2025, "week": 6, "date": "2025-10-13", "opp": "Kansas City Chiefs", "site": "A", "pf": 17, "pa": 30, "result": "L", "pr": 26.46, "pr_rank": NaN, "sos": 20.78, "sos_rank": 14.0, "opp_pr": 24.75, "opp_pr_rank": NaN, "opp_sos": 21.19, "opp_sos_rank": 8.0}, {"season": 2025, "week": 7, "date": "2025-10-20", "opp": "Tampa Bay Buccaneers", "site": "H", "pf": 24, "pa": 9, "result": "W", "pr": 25.52, "pr_rank": NaN, "sos": 22.24, "sos_rank": 3.0, "opp_pr": 22.31, "opp_pr_rank": NaN, "opp_sos": 20.77, "opp_sos_rank": 12.0}], "away_ytd": [{"season": 2025, "week": 1, "date": "2025-09-09", "opp": "Chicago Bears", "site": "A", "pf": 27.0, "pa": 24.0, "result": "W", "pr": 24.09, "pr_rank": NaN, "sos": 20.2, "sos_rank": 13.0, "opp_pr": 17.9, "opp_pr_rank": NaN, "opp_sos": 21.16, "opp_sos_rank": 2.0}, {"season": 2025, "week": 2, "date": "2025-09-15", "opp": "Atlanta Falcons", "site": "H", "pf": 6.0, "pa": 22.0, "result": "L", "pr": 20.34, "pr_rank": NaN, "sos": 19.14, "sos_rank": 21.0, "opp_pr": 19.81, "opp_pr_rank": NaN, "opp_sos": 21.09, "opp_sos_rank": 12.0}, {"season": 2025, "week": 3, "date": "2025-09-21", "opp": "Cincinnati Bengals", "site": "H", "pf": 48.0, "pa": 10.0, "result": "W", "pr": NaN, "pr_rank": NaN, "sos": NaN, "sos_rank": NaN, "opp_pr": NaN, "opp_pr_rank": NaN, "opp_sos": NaN, "opp_sos_rank": NaN}, {"season": 2025, "week": 4, "date": "2025-09-28", "opp": "Pittsburgh Steelers", "site": "A", "pf": 21.0, "pa": 24.0, "result": "L", "pr": 21.5, "pr_rank": NaN, "sos": 18.81, "sos_rank": 26.0, "opp_pr": 20.38, "opp_pr_rank": NaN, "opp_sos": 19.77, "opp_sos_rank": 20.0}, {"season": 2025, "week": 5, "date": "2025-10-05", "opp": "Cleveland Browns", "site": "A", "pf": 21.0, "pa": 17.0, "result": "W", "pr": 21.5, "pr_rank": NaN, "sos": 21.28, "sos_rank": 8.0, "opp_pr": 15.24, "opp_pr_rank": NaN, "opp_sos": 18.22, "opp_sos_rank": 28.0}, {"season": 2025, "week": 7, "date": "2025-10-19", "opp": "Philadelphia Eagles", "site": "H", "pf": 22.0, "pa": 28.0, "result": "L", "pr": 21.52, "pr_rank": NaN, "sos": 18.16, "sos_rank": 28.0, "opp_pr": 25.59, "opp_pr_rank": NaN, "opp_sos": 21.03, "opp_sos_rank": 9.0}, {"season": 2025, "week": 8, "date": "2025-10-24", "opp": "Los Angeles Chargers", "site": "A", "pf": NaN, "pa": NaN, "result": null, "pr": 21.52, "pr_rank": NaN, "sos": 18.16, "sos_rank": 28.0, "opp_pr": 20.95, "opp_pr_rank": NaN, "opp_sos": 20.67, "opp_sos_rank": 13.0}], "home_prev": [{"season": 2024, "week": 1, "date": "2024-09-09", "opp": "Los Angeles Rams", "site": "H", "pf": 26, "pa": 20, "result": "W", "pr": 25.09, "pr_rank": NaN, "sos": 19.33, "sos_rank": 21.0, "opp_pr": 21.44, "opp_pr_rank": NaN, "opp_sos": 27.2, "opp_sos_rank": 3.0}, {"season": 2024, "week": 2, "date": "2024-09-15", "opp": "Tampa Bay Buccaneers", "site": "H", "pf": 16, "pa": 20, "result": "L", "pr": NaN, "pr_rank": NaN, "sos": NaN, "sos_rank": NaN, "opp_pr": NaN, "opp_pr_rank": NaN, "opp_sos": NaN, "opp_sos_rank": NaN}, {"season": 2024, "week": 3, "date": "2024-09-22", "opp": "Arizona Cardinals", "site": "A", "pf": 20, "pa": 13, "result": "W", "pr": NaN, "pr_rank": NaN, "sos": NaN, "sos_rank": NaN, "opp_pr": NaN, "opp_pr_rank": NaN, "opp_sos": NaN, "opp_sos_rank": NaN}, {"season": 2024, "week": 4, "date": "2024-10-01", "opp": "Seattle Seahawks", "site": "H", "pf": 42, "pa": 29, "result": "W", "pr": NaN, "pr_rank": NaN, "sos": NaN, "sos_rank": NaN, "opp_pr": NaN, "opp_pr_rank": NaN, "opp_sos": NaN, "opp_sos_rank": NaN}, {"season": 2024, "week": 6, "date": "2024-10-13", "opp": "Dallas Cowboys", "site": "A", "pf": 47, "pa": 9, "result": "W", "pr": NaN, "pr_rank": NaN, "sos": NaN, "sos_rank": NaN, "opp_pr": NaN, "opp_pr_rank": NaN, "opp_sos": NaN, "opp_sos_rank": NaN}, {"season": 2024, "week": 7, "date": "2024-10-20", "opp": "Minnesota Vikings", "site": "A", "pf": 31, "pa": 29, "result": "W", "pr": NaN, "pr_rank": NaN, "sos": NaN, "sos_rank": NaN, "opp_pr": NaN, "opp_pr_rank": NaN, "opp_sos": NaN, "opp_sos_rank": NaN}, {"season": 2024, "week": 8, "date": "2024-10-27", "opp": "Tennessee Titans", "site": "H", "pf": 52, "pa": 14, "result": "W", "pr": NaN, "pr_rank": NaN, "sos": NaN, "sos_rank": NaN, "opp_pr": NaN, "opp_pr_rank": NaN, "opp_sos": NaN, "opp_sos_rank": NaN}, {"season": 2024, "week": 9, "date": "2024-11-03", "opp": "Green Bay Packers", "site": "A", "pf": 24, "pa": 14, "result": "W", "pr": NaN, "pr_rank": NaN, "sos": NaN, "sos_rank": NaN, "opp_pr": NaN, "opp_pr_rank": NaN, "opp_sos": NaN, "opp_sos_rank": NaN}, {"season": 2024, "week": 10, "date": "2024-11-11", "opp": "Houston Texans", "site": "A", "pf": 26, "pa": 23, "result": "W", "pr": NaN, "pr_rank": NaN, "sos": NaN, "sos_rank": NaN, "opp_pr": NaN, "opp_pr_rank": NaN, "opp_sos": NaN, "opp_sos_rank": NaN}, {"season": 2024, "week": 11, "date": "2024-11-17", "opp": "Jacksonville Jaguars", "site": "H", "pf": 52, "pa": 6, "result": "W", "pr": NaN, "pr_rank": NaN, "sos": NaN, "sos_rank": NaN, "opp_pr": NaN, "opp_pr_rank": NaN, "opp_sos": NaN, "opp_sos_rank": NaN}, {"season": 2024, "week": 12, "date": "2024-11-24", "opp": "Indianapolis Colts", "site": "A", "pf": 24, "pa": 6, "result": "W", "pr": 30.28, "pr_rank": NaN, "sos": 20.3, "sos_rank": 15.0, "opp_pr": 19.41, "opp_pr_rank": NaN, "opp_sos": 22.21, "opp_sos_rank": 3.0}, {"season": 2024, "week": 13, "date": "2024-11-28", "opp": "Chicago Bears", "site": "H", "pf": 23, "pa": 20, "result": "W", "pr": 29.68, "pr_rank": NaN, "sos": 20.11, "sos_rank": 14.0, "opp_pr": 19.73, "opp_pr_rank": NaN, "opp_sos": 19.86, "opp_sos_rank": 18.0}, {"season": 2024, "week": 14, "date": "2024-12-06", "opp": "Green Bay Packers", "site": "H", "pf": 34, "pa": 31, "result": "W", "pr": 29.49, "pr_rank": NaN, "sos": 20.52, "sos_rank": 11.0, "opp_pr": 26.05, "opp_pr_rank": NaN, "opp_sos": 21.62, "opp_sos_rank": 3.0}, {"season": 2024, "week": 15, "date": "2024-12-15", "opp": "Buffalo Bills", "site": "H", "pf": 42, "pa": 48, "result": "L", "pr": NaN, "pr_rank": NaN, "sos": NaN, "sos_rank": NaN, "opp_pr": NaN, "opp_pr_rank": NaN, "opp_sos": NaN, "opp_sos_rank": NaN}, {"season": 2024, "week": 16, "date": "2024-12-22", "opp": "Chicago Bears", "site": "A", "pf": 34, "pa": 17, "result": "W", "pr": NaN, "pr_rank": NaN, "sos": NaN, "sos_rank": NaN, "opp_pr": NaN, "opp_pr_rank": NaN, "opp_sos": NaN, "opp_sos_rank": NaN}, {"season": 2024, "week": 17, "date": "2024-12-31", "opp": "San Francisco 49ers", "site": "A", "pf": 40, "pa": 34, "result": "W", "pr": NaN, "pr_rank": NaN, "sos": NaN, "sos_rank": NaN, "opp_pr": NaN, "opp_pr_rank": NaN, "opp_sos": NaN, "opp_sos_rank": NaN}, {"season": 2024, "week": 18, "date": "2025-01-06", "opp": "Minnesota Vikings", "site": "H", "pf": 31, "pa": 9, "result": "W", "pr": 29.97, "pr_rank": NaN, "sos": 20.73, "sos_rank": 7.0, "opp_pr": 24.09, "opp_pr_rank": NaN, "opp_sos": 20.2, "opp_sos_rank": 13.0}, {"season": 2024, "week": 20, "date": "2025-01-19", "opp": "Washington Commanders", "site": "H", "pf": 31, "pa": 45, "result": "L", "pr": NaN, "pr_rank": NaN, "sos": NaN, "sos_rank": NaN, "opp_pr": NaN, "opp_pr_rank": NaN, "opp_sos": NaN, "opp_sos_rank": NaN}], "away_prev": [{"season": 2024, "week": 1, "date": "2024-09-08", "opp": "New York Giants", "site": "A", "pf": 28, "pa": 6, "result": "W", "pr": 20.01, "pr_rank": NaN, "sos": 15.26, "sos_rank": 26.0, "opp_pr": 13.15, "opp_pr_rank": NaN, "opp_sos": 17.9, "opp_sos_rank": 24.0}, {"season": 2024, "week": 2, "date": "2024-09-15", "opp": "San Francisco 49ers", "site": "H", "pf": 23, "pa": 17, "result": "W", "pr": NaN, "pr_rank": NaN, "sos": NaN, "sos_rank": NaN, "opp_pr": NaN, "opp_pr_rank": NaN, "opp_sos": NaN, "opp_sos_rank": NaN}, {"season": 2024, "week": 3, "date": "2024-09-22", "opp": "Houston Texans", "site": "H", "pf": 34, "pa": 7, "result": "W", "pr": NaN, "pr_rank": NaN, "sos": NaN, "sos_rank": NaN, "opp_pr": NaN, "opp_pr_rank": NaN, "opp_sos": NaN, "opp_sos_rank": NaN}, {"season": 2024, "week": 4, "date": "2024-09-29", "opp": "Green Bay Packers", "site": "A", "pf": 31, "pa": 29, "result": "W", "pr": NaN, "pr_rank": NaN, "sos": NaN, "sos_rank": NaN, "opp_pr": NaN, "opp_pr_rank": NaN, "opp_sos": NaN, "opp_sos_rank": NaN}, {"season": 2024, "week": 5, "date": "2024-10-06", "opp": "New York Jets", "site": "H", "pf": 23, "pa": 17, "result": "W", "pr": 24.1, "pr_rank": NaN, "sos": 21.74, "sos_rank": 3.0, "opp_pr": 21.8, "opp_pr_rank": NaN, "opp_sos": 19.56, "opp_sos_rank": 21.0}, {"season": 2024, "week": 7, "date": "2024-10-20", "opp": "Detroit Lions", "site": "H", "pf": 29, "pa": 31, "result": "L", "pr": NaN, "pr_rank": NaN, "sos": NaN, "sos_rank": NaN, "opp_pr": NaN, "opp_pr_rank": NaN, "opp_sos": NaN, "opp_sos_rank": NaN}, {"season": 2024, "week": 8, "date": "2024-10-25", "opp": "Los Angeles Rams", "site": "A", "pf": 20, "pa": 30, "result": "L", "pr": NaN, "pr_rank": NaN, "sos": NaN, "sos_rank": NaN, "opp_pr": NaN, "opp_pr_rank": NaN, "opp_sos": NaN, "opp_sos_rank": NaN}, {"season": 2024, "week": 9, "date": "2024-11-04", "opp": "Indianapolis Colts", "site": "H", "pf": 21, "pa": 13, "result": "W", "pr": NaN, "pr_rank": NaN, "sos": NaN, "sos_rank": NaN, "opp_pr": NaN, "opp_pr_rank": NaN, "opp_sos": NaN, "opp_sos_rank": NaN}, {"season": 2024, "week": 10, "date": "2024-11-10", "opp": "Jacksonville Jaguars", "site": "A", "pf": 12, "pa": 7, "result": "W", "pr": NaN, "pr_rank": NaN, "sos": NaN, "sos_rank": NaN, "opp_pr": NaN, "opp_pr_rank": NaN, "opp_sos": NaN, "opp_sos_rank": NaN}, {"season": 2024, "week": 11, "date": "2024-11-17", "opp": "Tennessee Titans", "site": "A", "pf": 23, "pa": 13, "result": "W", "pr": NaN, "pr_rank": NaN, "sos": NaN, "sos_rank": NaN, "opp_pr": NaN, "opp_pr_rank": NaN, "opp_sos": NaN, "opp_sos_rank": NaN}, {"season": 2024, "week": 12, "date": "2024-11-24", "opp": "Chicago Bears", "site": "A", "pf": 30, "pa": 27, "result": "W", "pr": 23.51, "pr_rank": NaN, "sos": 20.32, "sos_rank": 14.0, "opp_pr": 18.92, "opp_pr_rank": NaN, "opp_sos": 18.82, "opp_sos_rank": 25.0}, {"season": 2024, "week": 13, "date": "2024-12-01", "opp": "Arizona Cardinals", "site": "H", "pf": 23, "pa": 22, "result": "W", "pr": 23.23, "pr_rank": NaN, "sos": 20.12, "sos_rank": 13.0, "opp_pr": 20.8, "opp_pr_rank": NaN, "opp_sos": 22.41, "opp_sos_rank": 1.0}, {"season": 2024, "week": 14, "date": "2024-12-08", "opp": "Atlanta Falcons", "site": "H", "pf": 42, "pa": 21, "result": "W", "pr": 24.05, "pr_rank": NaN, "sos": 19.76, "sos_rank": 19.0, "opp_pr": 17.04, "opp_pr_rank": NaN, "opp_sos": 20.1, "opp_sos_rank": 16.0}, {"season": 2024, "week": 15, "date": "2024-12-17", "opp": "Chicago Bears", "site": "H", "pf": 30, "pa": 12, "result": "W", "pr": NaN, "pr_rank": NaN, "sos": NaN, "sos_rank": NaN, "opp_pr": NaN, "opp_pr_rank": NaN, "opp_sos": NaN, "opp_sos_rank": NaN}, {"season": 2024, "week": 16, "date": "2024-12-22", "opp": "Seattle Seahawks", "site": "A", "pf": 27, "pa": 24, "result": "W", "pr": NaN, "pr_rank": NaN, "sos": NaN, "sos_rank": NaN, "opp_pr": NaN, "opp_pr_rank": NaN, "opp_sos": NaN, "opp_sos_rank": NaN}, {"season": 2024, "week": 17, "date": "2024-12-29", "opp": "Green Bay Packers", "site": "H", "pf": 27, "pa": 25, "result": "W", "pr": NaN, "pr_rank": NaN, "sos": NaN, "sos_rank": NaN, "opp_pr": NaN, "opp_pr_rank": NaN, "opp_sos": NaN, "opp_sos_rank": NaN}, {"season": 2024, "week": 18, "date": "2025-01-06", "opp": "Detroit Lions", "site": "A", "pf": 9, "pa": 31, "result": "L", "pr": 24.09, "pr_rank": NaN, "sos": 20.2, "sos_rank": 13.0, "opp_pr": 29.97, "opp_pr_rank": NaN, "opp_sos": 20.73, "opp_sos_rank": 7.0}, {"season": 2024, "week": 19, "date": "2025-01-14", "opp": "Los Angeles Rams", "site": "A", "pf": 9, "pa": 27, "result": "L", "pr": NaN, "pr_rank": NaN, "sos": NaN, "sos_rank": NaN, "opp_pr": NaN, "opp_pr_rank": NaN, "opp_sos": NaN, "opp_sos_rank": NaN}]}